<annotation>
	<folder>parking</folder>
	<filename>IMG_1965.JPG</filename>
	<path>/Users/asimonov/Desktop/parking/IMG_1965.JPG</path>
	<source>
		<database>Unknown</database>
	</source>
	<size>
		<width>4032</width>
		<height>3024</height>
		<depth>3</depth>
	</size>
	<segmented>0</segmented>
	<object>
		<name>parking</name>
		<pose>Unspecified</pose>
		<truncated>0</truncated>
		<difficult>0</difficult>
		<bndbox>
			<xmin>2053</xmin>
			<ymin>1114</ymin>
			<xmax>2589</xmax>
			<ymax>1939</ymax>
		</bndbox>
	</object>
</annotation>
